flask_embed/__init__.py
Flask_Embed-0.0.1.dist-info/LICENSE
Flask_Embed-0.0.1.dist-info/METADATA
Flask_Embed-0.0.1.dist-info/WHEEL
Flask_Embed-0.0.1.dist-info/top_level.txt
Flask_Embed-0.0.1.dist-info/RECORD
