Metadata-Version: 2.2
Name: Flask-Embed
Version: 0.0.1
Summary: A Flask extension for embedding python code directly in HTML templates.
Author-email: Jaton Justice <jaton@pythonicit.com>
License: MIT License
Project-URL: Homepage, https://github.com/Masterjx9/Flask-Embed
Project-URL: Source, https://github.com/Masterjx9/Flask-Embed
Project-URL: Tracker, https://github.com/yourusername/flask-embed/issues
Keywords: flask,embed,jinja,extension
Requires-Python: >=3.7
License-File: LICENSE
